py_pdf_compress/__init__.py
py_pdf_compress/cli.py
py_pdf_compress/compress.py
py_pdf_compress-1.1.0.dist-info/licenses/LICENSE
py_pdf_compress-1.1.0.dist-info/METADATA
py_pdf_compress-1.1.0.dist-info/WHEEL
py_pdf_compress-1.1.0.dist-info/entry_points.txt
py_pdf_compress-1.1.0.dist-info/top_level.txt
py_pdf_compress-1.1.0.dist-info/RECORD
