Metadata-Version: 2.4
Name: py-pdf-compress
Version: 1.1.0
Summary: Compress all PDFs in the current directory using Ghostscript
Requires-Python: >=3.10
License-File: LICENSE
Dynamic: license-file
